OpenMediaBot/__init__.py
OpenMediaBot/bot.py
OpenMediaBot/twitter_bot.py
OpenMediaBot-1.1.3.dist-info/LICENSE
OpenMediaBot-1.1.3.dist-info/METADATA
OpenMediaBot-1.1.3.dist-info/WHEEL
OpenMediaBot-1.1.3.dist-info/top_level.txt
OpenMediaBot-1.1.3.dist-info/RECORD
