Metadata-Version: 2.1
Name: OpenMediaBot
Version: 1.1.3
Summary: A library for creating media bots.
Home-page: https://github.com/alexacallmebaka/OpenMediaBot
Author: alexacallmebaka
License: Apache License 2.0
Project-URL: Bug Tracker, https://github.com/alexacallmebaka/OpenMediaBot/issues
Platform: UNKNOWN
Classifier: Programming Language :: Python :: 3
Classifier: License :: OSI Approved :: Apache Software License
Classifier: Operating System :: OS Independent
Classifier: Development Status :: 5 - Production/Stable
Requires-Python: >=3.7
License-File: LICENSE
Requires-Dist: pydrive2
Requires-Dist: twython
Requires-Dist: simplejson
Requires-Dist: pillow
